sheatless/__init__.py
sheatless/api.py
sheatless/engine.py
sheatless/pdf_predictor.py
sheatless-1.9.7.dist-info/LICENSE
sheatless-1.9.7.dist-info/METADATA
sheatless-1.9.7.dist-info/WHEEL
sheatless-1.9.7.dist-info/top_level.txt
sheatless-1.9.7.dist-info/RECORD
