Metadata-Version: 2.1
Name: sheatless
Version: 1.9.7
Summary: A python library for extracting parts from sheetmusic pdfs
Home-page: https://gitlab.com/taktlause/sheatless
Author: The Beatless
Project-URL: Bug Tracker, https://gitlab.com/taktlause/sheatless/-/issues
Classifier: Programming Language :: Python :: 3
Classifier: License :: OSI Approved :: GNU Affero General Public License v3
Classifier: Operating System :: OS Independent
Requires-Python: >=3.10
License-File: LICENSE
Requires-Dist: Pillow>=9.0.0
Requires-Dist: PyPDF2~=2.12
Requires-Dist: opencv-python-headless>=4.5.5.62
Requires-Dist: pdf2image>=1.16.0
Requires-Dist: pytesseract>=0.3.8
Requires-Dist: tesserocr>=2.5.2
Requires-Dist: pyyaml>=6.0
Requires-Dist: unidecode>=1.3.2
